{
  "name": "Julia Gilbert",
  "age": 50,
  "address": {
    "street": "Zebfa Heights",
    "city": "Uvkambe",
    "state": "MO",
    "zip": "29663"
  },
  "contact": {
    "phone": "(368) 572-1253",
    "servicePhone": "800864633"
  },
  "birthday": "1968-02-11T16:05:35.818Z",
  "ip": "205.158.119.250",
  "foo": "bar",
  "profile": {
    "about": "Ono gil li fu emi lum hozo pimetopo ujleb moreej idci vilzurto livuvo avurof ocfek werej. Waz duucesol gakus zokeg webefe kiso berdawvu mikin tejzac no satuwan hojma il wu edejeros. Sokfu isa feronwup jug ta naz elcor cewe dunpohem jonus um wi fa. Mudvo da ni weheaz juwdicjic irvizof cu mahum pefalne ukamom uhirud eblikba paf ofavoc cuwed. Vob tameg tol ecacipo ku nepiplav zerraler pewaksat gaf lefjaadu ziopjav oli gak fanpa.",
    "bio": "Pajle jahovu to gucipa ri supdasniw mudih ajadibe izpu weceri bu ziuscih wulari nu wap uhot. Fadgofi idek tuj pabfahti mi mu tuj sogov ka ija seh so hopeb. Lerjo tithe redehko kuim gelkuf uri nonre todujdet de lazro ipu lovti emu ziropguz. Dubeb kudec toiv gagkecra ohfopto jifzivol ihihe ros hu civenobu hutfo rufnanev ukinafi parlawkal ko pa acuulo."
  },
  "apiKey": "f02227d1548a1f9879629807161bd1e09b5ebf63f81b8870527608d9171195c5",
  "currency": {
    "code": "BDT",
    "name": "Bangladesh Taka"
  }
}