{
  "name": "Lottie Daniel",
  "age": 27,
  "address": {
    "street": "Fizbaw Turnpike",
    "city": "Ikaweug",
    "state": "ME",
    "zip": "46524"
  },
  "contact": {
    "phone": "(412) 774-9232",
    "servicePhone": "800934126"
  },
  "birthday": "1998-06-15T21:18:37.830Z",
  "ip": "250.235.41.201",
  "foo": "bar",
  "profile": {
    "about": "Bieskup da hikago bu baf rigup etu velidedo pakga cum posvaku bislolco ijpefenu tovcedkof. Zuzad induv nobla em sazu puwpucwi mofodfod ek mu wadow doga hocbu nojdo. Lohur meas mohgu is depfizmo ahugic ce aj baljebseb jamzo nutuwfa habibom uce bokuda mu wi joiva lu.",
    "bio": "Dizuis fifot cilmiwe ge ujsim pik zibdidno zat burahusi najuv az cu laktur ki hibiiti. Buze ec jeza jor had geovheg gajote goebguh hodtal tihnoz ci jel. Ipuohzo beb co fu zew mah linaro tonnitko togduhbel icesujul iza soc gucoizi bac. Nigno cugej imdipfog wauk ofapode pol hermoig malwab tolefuf jonve vule jusajdu nafilib ohcem zo dul. Gogeare ge runhapav ke ujene bol menala opve zadja dogteku kailu peoheod meg puz somjofake goda zuzfirori venpoan."
  },
  "apiKey": "222c44e3d7dfa4775c3a31588b48f916abfe4654147b7e74b96cf19a23224657",
  "currency": {
    "code": "MWK",
    "name": "Malawi Kwacha"
  }
}